opencepk_lib_python_common/__init__.py
opencepk_lib_python_common/find_and_replace_strings_package/__init__.py
opencepk_lib_python_common/find_and_replace_strings_package/find_and_replace_strings/__init__.py
opencepk_lib_python_common/find_and_replace_strings_package/find_and_replace_strings/__main__.py
opencepk_lib_python_common/find_and_replace_strings_package/find_and_replace_strings/main.py
opencepk_lib_python_common/find_and_replace_strings_package/tests/__init__.py
opencepk_lib_python_common/find_and_replace_strings_package/tests/test_main.py
opencepk_lib_python_common/pypi_bumpversion_check_package/__init__.py
opencepk_lib_python_common/pypi_bumpversion_check_package/pypi_bumpversion_check/__init__.py
opencepk_lib_python_common/pypi_bumpversion_check_package/pypi_bumpversion_check/__main__.py
opencepk_lib_python_common/pypi_bumpversion_check_package/pypi_bumpversion_check/main.py
opencepk_lib_python_common-1.2.0.dist-info/LICENSE
opencepk_lib_python_common-1.2.0.dist-info/METADATA
opencepk_lib_python_common-1.2.0.dist-info/WHEEL
opencepk_lib_python_common-1.2.0.dist-info/entry_points.txt
opencepk_lib_python_common-1.2.0.dist-info/top_level.txt
opencepk_lib_python_common-1.2.0.dist-info/RECORD
